scapy_unroot/__init__.py
scapy_unroot/daemon.py
scapy_unroot/sockets.py
tests/__init__.py
tests/daemon.py
tests/sockets.py
scapy_unroot-0.3.0b4.dist-info/LICENSE
scapy_unroot-0.3.0b4.dist-info/METADATA
scapy_unroot-0.3.0b4.dist-info/WHEEL
scapy_unroot-0.3.0b4.dist-info/entry_points.txt
scapy_unroot-0.3.0b4.dist-info/top_level.txt
scapy_unroot-0.3.0b4.dist-info/RECORD
